{
  "name": "Shopsys Platform Core",
  "parent_id": 152164406559162,
  "group_id": "fca8ee8d-cdf1-4d8a-832f-261d49b5073d",
  "alternates": [],
  "created_at": "2026-03-12T23:10:39.182Z",
  "deleted_at": null,
  "sort_by_date": null,
  "tag_list": [],
  "updated_at": "2026-03-13T14:31:42.615Z",
  "published_at": "2026-03-13T14:31:42.548Z",
  "id": 154285830931674,
  "uuid": "267948bb-d9da-4905-b35e-b91033037a80",
  "is_folder": false,
  "content": {
    "seo": [
      {
        "_uid": "bef0b677-07c9-e060-b47f-645e083334de",
        "noindex": false,
        "component": "seo_meta",
        "meta_title": "Shopsys Platform Core",
        "meta_description": "Shared e-commerce storefront platform at Shopsys built on Next.js Pages Router, React, TypeScript, URQL, and generated GraphQL operations, with Cypress and Vitest coverage for reusable project implementations."
      }
    ],
    "_uid": "6abdb865-2278-43a7-b031-f0ebae5731b5",
    "slug": "shopsys-platform-core",
    "type": "E-commerce Frontend Platform",
    "stack": [
      "Next.js Pages Router",
      "React",
      "TypeScript",
      "URQL",
      "GraphQL Codegen",
      "Cypress",
      "Vitest",
      "Docker Review Apps"
    ],
    "title": "Shopsys Platform Core",
    "content": {
      "type": "doc",
      "content": [
        {
          "type": "paragraph",
          "content": [
            {
              "text": "At Shopsys, I work on the shared storefront core used as the frontend base for multiple e-commerce implementations. The codebase is organized around Next.js Pages Router, React, TypeScript, Zustand, URQL, and generated GraphQL operations against the platform frontend API.",
              "type": "text"
            }
          ]
        },
        {
          "type": "paragraph",
          "content": [
            {
              "text": "The work is platform-oriented rather than project-local: reusable order and payment flows, generated types, storefront architecture, Tailwind export for admin integration, and delivery that fits Dockerized development together with branch review deployments and GitHub Actions workflows.",
              "type": "text"
            }
          ]
        },
        {
          "type": "paragraph",
          "content": [
            {
              "text": "My recent work has focused on GoPay and payment reliability: hardening return and confirmation flows, stabilizing payment-status handling and GTM deduplication, updating GraphQL operations and generated types, adding Vitest and Cypress regression coverage, and verifying iframe-sensitive changes on real HTTPS review branches with Playwright evidence.",
              "type": "text"
            }
          ]
        }
      ]
    },
    "summary": "Shared e-commerce storefront platform at Shopsys built on Next.js Pages Router, React, TypeScript, URQL, and generated GraphQL operations, with Cypress and Vitest coverage for reusable project implementations.",
    "component": "page_project",
    "project_url": "https://www.shopsys.cz/",
    "published_date": "2024-06-06 00:00",
    "repository_url": "https://github.com/shopsys/shopsys",
    "portfolio_priority": 1
  },
  "published": true,
  "slug": "shopsys-platform-core",
  "path": null,
  "full_slug": "projects/shopsys-platform-core",
  "default_root": null,
  "disble_fe_editor": false,
  "disable_fe_editor": false,
  "parent": {
    "id": 152164406559162,
    "uuid": "bf96e0c5-77d2-45a5-b951-50deed345b87",
    "name": "Projects",
    "slug": "projects",
    "disble_fe_editor": false
  },
  "is_startpage": false,
  "unpublished_changes": false,
  "meta_data": null,
  "imported_at": null,
  "preview_token": {
    "token": "8289fbe54ce7030b1e12e47b27ba3e1b32aa0789",
    "timestamp": "1773412306"
  },
  "pinned": false,
  "breadcrumbs": [
    {
      "id": 152164406559162,
      "name": "Projects",
      "parent_id": 0,
      "disble_fe_editor": false,
      "disable_fe_editor": false,
      "path": null,
      "slug": "projects",
      "translated_slugs": []
    }
  ],
  "publish_at": null,
  "expire_at": null,
  "first_published_at": "2026-03-12T23:10:42.279Z",
  "last_author": {
    "id": 149154938651357,
    "userid": "JanMolcik",
    "friendly_name": "Jan Molčík"
  },
  "last_author_id": 149154938651357,
  "user_ids": [],
  "space_role_ids": [],
  "translated_slugs": [],
  "localized_paths": [],
  "position": -80,
  "translated_stories": [],
  "can_not_view": false,
  "is_scheduled": null,
  "scheduled_dates": null,
  "ideas": [],
  "current_version_id": 154512171179804,
  "stage": null,
  "favourite_for_user_ids": []
}